UE4Parse/BinaryReader.py
UE4Parse/Logger.py
UE4Parse/Oodle.py
UE4Parse/__init__.py
UE4Parse/Assets/PackageReader.py
UE4Parse/Assets/ToJson.py
UE4Parse/Assets/__init__.py
UE4Parse/Assets/Exports/ExportRegistry.py
UE4Parse/Assets/Exports/Level.py
UE4Parse/Assets/Exports/MaterialInstanceConstant.py
UE4Parse/Assets/Exports/UClass.py
UE4Parse/Assets/Exports/UObjects.py
UE4Parse/Assets/Exports/UStringTable.py
UE4Parse/Assets/Exports/World.py
UE4Parse/Assets/Exports/__init__.py
UE4Parse/Assets/Exports/Engine/UCurveTable.py
UE4Parse/Assets/Exports/Engine/UDataTable.py
UE4Parse/Assets/Exports/Engine/__init__.py
UE4Parse/Assets/Exports/StaticMesh/FDistanceFieldVolumeData.py
UE4Parse/Assets/Exports/StaticMesh/FPositionVertexBuffer.py
UE4Parse/Assets/Exports/StaticMesh/FRawStaticIndexBuffer.py
UE4Parse/Assets/Exports/StaticMesh/FStaticMaterial.py
UE4Parse/Assets/Exports/StaticMesh/FStaticMeshLODResources.py
UE4Parse/Assets/Exports/StaticMesh/FStaticMeshSection.py
UE4Parse/Assets/Exports/StaticMesh/FStaticMeshUVItem.py
UE4Parse/Assets/Exports/StaticMesh/FStaticMeshVertexBuffer.py
UE4Parse/Assets/Exports/StaticMesh/UStaticMesh.py
UE4Parse/Assets/Exports/StaticMesh/__init__.py
UE4Parse/Assets/Exports/Textures/Decoder.py
UE4Parse/Assets/Exports/Textures/ULightMapTexture2D.py
UE4Parse/Assets/Exports/Textures/UTexture2D.py
UE4Parse/Assets/Exports/Textures/UTextureCube.py
UE4Parse/Assets/Exports/Textures/UVolumeTexture.py
UE4Parse/Assets/Exports/Textures/__init__.py
UE4Parse/Assets/Exports/Textures/utils.cp39-win_amd64.pyd
UE4Parse/Assets/Exports/Textures/Objects/FTexture2DMipMap.py
UE4Parse/Assets/Exports/Textures/Objects/FTexturePlatformData.py
UE4Parse/Assets/Exports/Textures/Objects/__init__.py
UE4Parse/Assets/Objects/Decompress.py
UE4Parse/Assets/Objects/EBulkDataFlags.py
UE4Parse/Assets/Objects/EObjectFlags.py
UE4Parse/Assets/Objects/EPackageFlags.py
UE4Parse/Assets/Objects/EPixelFormat.py
UE4Parse/Assets/Objects/EReleaseObjectVersion.py
UE4Parse/Assets/Objects/ETextFlag.py
UE4Parse-0.0.1.dist-info/LICENSE
UE4Parse-0.0.1.dist-info/METADATA
UE4Parse-0.0.1.dist-info/WHEEL
UE4Parse-0.0.1.dist-info/top_level.txt
UE4Parse-0.0.1.dist-info/RECORD
