Metadata-Version: 2.1
Name: UE4Parse
Version: 0.0.1
Summary: ue4 asset parser
Home-page: https://github.com/MinshuG/UE4Parse
Author: MinshuG
License: UNKNOWN
Platform: UNKNOWN
Classifier: Programming Language :: Python :: 3
Classifier: License :: OSI Approved :: MIT License
Requires-Dist: pycryptodome
Requires-Dist: lz4
Requires-Dist: pyUsmap
Requires-Dist: pillow
Requires-Dist: quicktex
Requires-Dist: astc-decomp
